league_analysis_mcp_server/__init__.py
league_analysis_mcp_server/__main__.py
league_analysis_mcp_server/analytics.py
league_analysis_mcp_server/cache.py
league_analysis_mcp_server/enhanced_auth.py
league_analysis_mcp_server/enhancement_helpers.py
league_analysis_mcp_server/game_tools.py
league_analysis_mcp_server/historical.py
league_analysis_mcp_server/oauth_callback_server.py
league_analysis_mcp_server/player_tools.py
league_analysis_mcp_server/py.typed
league_analysis_mcp_server/resources.py
league_analysis_mcp_server/server.py
league_analysis_mcp_server/shared_utils.py
league_analysis_mcp_server/team_tools.py
league_analysis_mcp_server/tools.py
league_analysis_mcp_server/tools_impl.py
league_analysis_mcp_server/utility_tools.py
league_analysis_mcp_server/config/game_ids.json
league_analysis_mcp_server/config/settings.json
league_analysis_mcp_server-0.3.1.dist-info/METADATA
league_analysis_mcp_server-0.3.1.dist-info/WHEEL
league_analysis_mcp_server-0.3.1.dist-info/entry_points.txt
league_analysis_mcp_server-0.3.1.dist-info/RECORD
