Metadata-Version: 2.4
Name: league-analysis-mcp-server
Version: 0.3.1
Summary: Model Context Protocol server for Yahoo Fantasy Sports API with advanced historical analysis and manager profiling
Project-URL: Homepage, https://github.com/ari1110/League-Analysis-MCP
Project-URL: Repository, https://github.com/ari1110/League-Analysis-MCP.git
Project-URL: Issues, https://github.com/ari1110/League-Analysis-MCP/issues
Project-URL: Documentation, https://github.com/ari1110/League-Analysis-MCP#readme
Project-URL: Changelog, https://github.com/ari1110/League-Analysis-MCP/blob/main/CHANGELOG.md
Author-email: League Analysis MCP <info@league-analysis-mcp.com>
License: MIT
Keywords: ai-assistant,analytics,fantasy-sports,mcp,mlb,model-context-protocol,nba,nfl,nhl,yahoo-fantasy
Classifier: Development Status :: 4 - Beta
Classifier: Framework :: AsyncIO
Classifier: Intended Audience :: Developers
Classifier: Intended Audience :: End Users/Desktop
Classifier: License :: OSI Approved :: MIT License
Classifier: Operating System :: OS Independent
Classifier: Programming Language :: Python :: 3
Classifier: Programming Language :: Python :: 3.10
Classifier: Programming Language :: Python :: 3.11
Classifier: Programming Language :: Python :: 3.12
Classifier: Topic :: Games/Entertainment
Classifier: Topic :: Scientific/Engineering :: Information Analysis
Classifier: Topic :: Software Development :: Libraries :: Python Modules
Requires-Python: >=3.10
Requires-Dist: asyncio-throttle>=1.0.0
Requires-Dist: cryptography>=3.0.0
Requires-Dist: fastmcp>=2.0.0
Requires-Dist: pandas>=2.0.0
Requires-Dist: pydantic>=2.0.0
Requires-Dist: python-dotenv>=1.0.0
Requires-Dist: requests>=2.31.0
Requires-Dist: yfpy>=16.0.0
Provides-Extra: dev
Requires-Dist: black>=23.0.0; extra == 'dev'
Requires-Dist: flake8>=7.1.1; extra == 'dev'
Requires-Dist: isort>=5.12.0; extra == 'dev'
Requires-Dist: mypy>=1.17.1; extra == 'dev'
Requires-Dist: pyright>=1.1.405; extra == 'dev'
Requires-Dist: pytest-asyncio>=0.21.0; extra == 'dev'
Requires-Dist: pytest>=7.0.0; extra == 'dev'
Requires-Dist: types-requests>=2.32.4.20250809; extra == 'dev'
